{"cameraMode":{"drawMode":0,"name":"Shaded","section":"Shading Mode"},"sceneLighting":false,"audioPlay":false,"sceneViewState":{"showFog":false,"showMaterialUpdate":false,"showSkybox":false,"showFlares":false,"showImageEffects":false,"showParticleSystems":false,"showVisualEffectGraphs":true,"m_FxEnabled":true},"in2DMode":false,"pivot":{"x":2.933727741241455,"y":-3.098874092102051,"z":-3.723849296569824},"rotation":{"x":0.0157419815659523,"y":0.8932816982269287,"z":-0.44815272092819216,"w":0.03137846663594246},"size":14.12833309173584,"orthographic":false}